GPUDTW/OpenCL.dll
GPUDTW/README.cn.md
GPUDTW/README.md
GPUDTW/__init__.py
GPUDTW/cpudtw.py
GPUDTW/cudadtw.cu
GPUDTW/cudadtw.py
GPUDTW/opencldtw.cl
GPUDTW/opencldtw.py
GPUDTW/test.py
GPUDTW-0.13.dist-info/LICENSE
GPUDTW-0.13.dist-info/METADATA
GPUDTW-0.13.dist-info/WHEEL
GPUDTW-0.13.dist-info/top_level.txt
GPUDTW-0.13.dist-info/RECORD
