Metadata-Version: 2.1
Name: GPUDTW
Version: 0.13
Summary: dynamic time warping (DTW) by GPU accelerated
Home-page: https://github.com/qianlikzf/GPUDTW
Author: Wang Zihao
Author-email: qianlkzf@outlook.com
License: GNU GENERAL PUBLIC LICENSE Version 3
Keywords: DTW,GPU,OpenCL,CUDA
Classifier: Programming Language :: Python :: 3
Classifier: License :: OSI Approved :: GNU General Public License v3 (GPLv3)
Classifier: Operating System :: OS Independent
License-File: LICENSE
Requires-Dist: numpy
Requires-Dist: numba
